{"content": {"suites": {"0": {"status": {"total_pass": 100, "total_skip": 0, "total_xpass": 0, "total_xfail": 0, "total_rerun": 0, "total_fail": 0, "total_error": 0}, "tests": {"0": {"status": "PASS", "message": "", "test_name": "test_server_get_historical_1[1-50]", "rerun": "0"}, "1": {"status": "PASS", "message": "", "test_name": "test_server_get_historical_1[2-50]", "rerun": "0"}, "2": {"status": "PASS", "message": "", "test_name": "test_server_get_historical_1[3-50]", "rerun": "0"}, "3": {"status": "PASS", "message": "", "test_name": "test_server_get_historical_1[4-50]", "rerun": "0"}, "4": {"status": "PASS", "message": "", "test_name": "test_server_get_historical_1[5-50]", "rerun": "0"}, "5": {"status": "PASS", "message": "", "test_name": "test_server_get_historical_1[6-50]", "rerun": "0"}, "6": {"status": "PASS", "message": "", "test_name": "test_server_get_historical_1[7-50]", "rerun": "0"}, "7": {"status": "PASS", "message": "", "test_name": "test_server_get_historical_1[8-50]", "rerun": "0"}, "8": {"status": "PASS", "message": "", "test_name": "test_server_get_historical_1[9-50]", "rerun": "0"}, "9": {"status": "PASS", "message": "", "test_name": "test_server_get_historical_1[10-50]", "rerun": "0"}, "10": {"status": "PASS", "message": "", "test_name": "test_server_get_historical_1[11-50]", "rerun": "0"}, "11": {"status": "PASS", "message": "", "test_name": "test_server_get_historical_1[12-50]", "rerun": "0"}, "12": {"status": "PASS", "message": "", "test_name": "test_server_get_historical_1[13-50]", "rerun": "0"}, "13": {"status": "PASS", "message": "", "test_name": "test_server_get_historical_1[14-50]", "rerun": "0"}, "14": {"status": "PASS", "message": "", "test_name": "test_server_get_historical_1[15-50]", "rerun": "0"}, "15": {"status": "PASS", "message": "", "test_name": "test_server_get_historical_1[16-50]", "rerun": "0"}, "16": {"status": "PASS", "message": "", "test_name": "test_server_get_historical_1[17-50]", "rerun": "0"}, "17": {"status": "PASS", "message": "", "test_name": "test_server_get_historical_1[18-50]", "rerun": "0"}, "18": {"status": "PASS", "message": "", "test_name": "test_server_get_historical_1[19-50]", "rerun": "0"}, "19": {"status": "PASS", "message": "", "test_name": "test_server_get_historical_1[20-50]", "rerun": "0"}, "20": {"status": "PASS", "message": "", "test_name": "test_server_get_historical_1[21-50]", "rerun": "0"}, "21": {"status": "PASS", "message": "", "test_name": "test_server_get_historical_1[22-50]", "rerun": "0"}, "22": {"status": "PASS", "message": "", "test_name": "test_server_get_historical_1[23-50]", "rerun": "0"}, "23": {"status": "PASS", "message": "", "test_name": "test_server_get_historical_1[24-50]", "rerun": "0"}, "24": {"status": "PASS", "message": "", "test_name": "test_server_get_historical_1[25-50]", "rerun": "0"}, "25": {"status": "PASS", "message": "", "test_name": "test_server_get_historical_1[26-50]", "rerun": "0"}, "26": {"status": "PASS", "message": "", "test_name": "test_server_get_historical_1[27-50]", "rerun": "0"}, "27": {"status": "PASS", "message": "", "test_name": "test_server_get_historical_1[28-50]", "rerun": "0"}, "28": {"status": "PASS", "message": "", "test_name": "test_server_get_historical_1[29-50]", "rerun": "0"}, "29": {"status": "PASS", "message": "", "test_name": "test_server_get_historical_1[30-50]", "rerun": "0"}, "30": {"status": "PASS", "message": "", "test_name": "test_server_get_historical_1[31-50]", "rerun": "0"}, "31": {"status": "PASS", "message": "", "test_name": "test_server_get_historical_1[32-50]", "rerun": "0"}, "32": {"status": "PASS", "message": "", "test_name": "test_server_get_historical_1[33-50]", "rerun": "0"}, "33": {"status": "PASS", "message": "", "test_name": "test_server_get_historical_1[34-50]", "rerun": "0"}, "34": {"status": "PASS", "message": "", "test_name": "test_server_get_historical_1[35-50]", "rerun": "0"}, "35": {"status": "PASS", "message": "", "test_name": "test_server_get_historical_1[36-50]", "rerun": "0"}, "36": {"status": "PASS", "message": "", "test_name": "test_server_get_historical_1[37-50]", "rerun": "0"}, "37": {"status": "PASS", "message": "", "test_name": "test_server_get_historical_1[38-50]", "rerun": "0"}, "38": {"status": "PASS", "message": "", "test_name": "test_server_get_historical_1[39-50]", "rerun": "0"}, "39": {"status": "PASS", "message": "", "test_name": "test_server_get_historical_1[40-50]", "rerun": "0"}, "40": {"status": "PASS", "message": "", "test_name": "test_server_get_historical_1[41-50]", "rerun": "0"}, "41": {"status": "PASS", "message": "", "test_name": "test_server_get_historical_1[42-50]", "rerun": "0"}, "42": {"status": "PASS", "message": "", "test_name": "test_server_get_historical_1[43-50]", "rerun": "0"}, "43": {"status": "PASS", "message": "", "test_name": "test_server_get_historical_1[44-50]", "rerun": "0"}, "44": {"status": "PASS", "message": "", "test_name": "test_server_get_historical_1[45-50]", "rerun": "0"}, "45": {"status": "PASS", "message": "", "test_name": "test_server_get_historical_1[46-50]", "rerun": "0"}, "46": {"status": "PASS", "message": "", "test_name": "test_server_get_historical_1[47-50]", "rerun": "0"}, "47": {"status": "PASS", "message": "", "test_name": "test_server_get_historical_1[48-50]", "rerun": "0"}, "48": {"status": "PASS", "message": "", "test_name": "test_server_get_historical_1[49-50]", "rerun": "0"}, "49": {"status": "PASS", "message": "", "test_name": "test_server_get_historical_1[50-50]", "rerun": "0"}, "50": {"status": "PASS", "message": "", "test_name": "test_server_get_historical_2[1-50]", "rerun": "0"}, "51": {"status": "PASS", "message": "", "test_name": "test_server_get_historical_2[2-50]", "rerun": "0"}, "52": {"status": "PASS", "message": "", "test_name": "test_server_get_historical_2[3-50]", "rerun": "0"}, "53": {"status": "PASS", "message": "", "test_name": "test_server_get_historical_2[4-50]", "rerun": "0"}, "54": {"status": "PASS", "message": "", "test_name": "test_server_get_historical_2[5-50]", "rerun": "0"}, "55": {"status": "PASS", "message": "", "test_name": "test_server_get_historical_2[6-50]", "rerun": "0"}, "56": {"status": "PASS", "message": "", "test_name": "test_server_get_historical_2[7-50]", "rerun": "0"}, "57": {"status": "PASS", "message": "", "test_name": "test_server_get_historical_2[8-50]", "rerun": "0"}, "58": {"status": "PASS", "message": "", "test_name": "test_server_get_historical_2[9-50]", "rerun": "0"}, "59": {"status": "PASS", "message": "", "test_name": "test_server_get_historical_2[10-50]", "rerun": "0"}, "60": {"status": "PASS", "message": "", "test_name": "test_server_get_historical_2[11-50]", "rerun": "0"}, "61": {"status": "PASS", "message": "", "test_name": "test_server_get_historical_2[12-50]", "rerun": "0"}, "62": {"status": "PASS", "message": "", "test_name": "test_server_get_historical_2[13-50]", "rerun": "0"}, "63": {"status": "PASS", "message": "", "test_name": "test_server_get_historical_2[14-50]", "rerun": "0"}, "64": {"status": "PASS", "message": "", "test_name": "test_server_get_historical_2[15-50]", "rerun": "0"}, "65": {"status": "PASS", "message": "", "test_name": "test_server_get_historical_2[16-50]", "rerun": "0"}, "66": {"status": "PASS", "message": "", "test_name": "test_server_get_historical_2[17-50]", "rerun": "0"}, "67": {"status": "PASS", "message": "", "test_name": "test_server_get_historical_2[18-50]", "rerun": "0"}, "68": {"status": "PASS", "message": "", "test_name": "test_server_get_historical_2[19-50]", "rerun": "0"}, "69": {"status": "PASS", "message": "", "test_name": "test_server_get_historical_2[20-50]", "rerun": "0"}, "70": {"status": "PASS", "message": "", "test_name": "test_server_get_historical_2[21-50]", "rerun": "0"}, "71": {"status": "PASS", "message": "", "test_name": "test_server_get_historical_2[22-50]", "rerun": "0"}, "72": {"status": "PASS", "message": "", "test_name": "test_server_get_historical_2[23-50]", "rerun": "0"}, "73": {"status": "PASS", "message": "", "test_name": "test_server_get_historical_2[24-50]", "rerun": "0"}, "74": {"status": "PASS", "message": "", "test_name": "test_server_get_historical_2[25-50]", "rerun": "0"}, "75": {"status": "PASS", "message": "", "test_name": "test_server_get_historical_2[26-50]", "rerun": "0"}, "76": {"status": "PASS", "message": "", "test_name": "test_server_get_historical_2[27-50]", "rerun": "0"}, "77": {"status": "PASS", "message": "", "test_name": "test_server_get_historical_2[28-50]", "rerun": "0"}, "78": {"status": "PASS", "message": "", "test_name": "test_server_get_historical_2[29-50]", "rerun": "0"}, "79": {"status": "PASS", "message": "", "test_name": "test_server_get_historical_2[30-50]", "rerun": "0"}, "80": {"status": "PASS", "message": "", "test_name": "test_server_get_historical_2[31-50]", "rerun": "0"}, "81": {"status": "PASS", "message": "", "test_name": "test_server_get_historical_2[32-50]", "rerun": "0"}, "82": {"status": "PASS", "message": "", "test_name": "test_server_get_historical_2[33-50]", "rerun": "0"}, "83": {"status": "PASS", "message": "", "test_name": "test_server_get_historical_2[34-50]", "rerun": "0"}, "84": {"status": "PASS", "message": "", "test_name": "test_server_get_historical_2[35-50]", "rerun": "0"}, "85": {"status": "PASS", "message": "", "test_name": "test_server_get_historical_2[36-50]", "rerun": "0"}, "86": {"status": "PASS", "message": "", "test_name": "test_server_get_historical_2[37-50]", "rerun": "0"}, "87": {"status": "PASS", "message": "", "test_name": "test_server_get_historical_2[38-50]", "rerun": "0"}, "88": {"status": "PASS", "message": "", "test_name": "test_server_get_historical_2[39-50]", "rerun": "0"}, "89": {"status": "PASS", "message": "", "test_name": "test_server_get_historical_2[40-50]", "rerun": "0"}, "90": {"status": "PASS", "message": "", "test_name": "test_server_get_historical_2[41-50]", "rerun": "0"}, "91": {"status": "PASS", "message": "", "test_name": "test_server_get_historical_2[42-50]", "rerun": "0"}, "92": {"status": "PASS", "message": "", "test_name": "test_server_get_historical_2[43-50]", "rerun": "0"}, "93": {"status": "PASS", "message": "", "test_name": "test_server_get_historical_2[44-50]", "rerun": "0"}, "94": {"status": "PASS", "message": "", "test_name": "test_server_get_historical_2[45-50]", "rerun": "0"}, "95": {"status": "PASS", "message": "", "test_name": "test_server_get_historical_2[46-50]", "rerun": "0"}, "96": {"status": "PASS", "message": "", "test_name": "test_server_get_historical_2[47-50]", "rerun": "0"}, "97": {"status": "PASS", "message": "", "test_name": "test_server_get_historical_2[48-50]", "rerun": "0"}, "98": {"status": "PASS", "message": "", "test_name": "test_server_get_historical_2[49-50]", "rerun": "0"}, "99": {"status": "PASS", "message": "", "test_name": "test_server_get_historical_2[50-50]", "rerun": "0"}}, "suite_name": "time_test.py"}}}, "date": "January 07, 2022", "start_time": 1641560372.861169, "total_suite": 1, "status": "PASS", "status_list": {"pass": "100", "fail": "0", "skip": "0", "error": "0", "xpass": "0", "xfail": "0", "rerun": "0"}, "total_tests": "100"}